nonebot_plugin_df_armor_repair_simulator/__init__.py
nonebot_plugin_df_armor_repair_simulator-0.0.3.dist-info/LICENSE
nonebot_plugin_df_armor_repair_simulator-0.0.3.dist-info/METADATA
nonebot_plugin_df_armor_repair_simulator-0.0.3.dist-info/WHEEL
nonebot_plugin_df_armor_repair_simulator-0.0.3.dist-info/RECORD
